{
  "status": "passed",
  "webUrl": "http://127.0.0.1:9999",
  "backendUrl": "http://127.0.0.1:8787",
  "quickClarificationStatus": "快速澄清\ndone",
  "artifactStatus": "完整 DSL artifacts\ndone",
  "runId": "RUN-20260609-190415-LXO0C",
  "outputDirVisible": true,
  "sourceProviderVisible": true,
  "realModelVisible": true,
  "mockUsed": false,
  "retryExercised": false,
  "retryRunId": "",
  "oldRunnerMissingVisible": false,
  "pageVerticalScroll": false,
  "consoleErrors": [],
  "pageErrors": [],
  "processLogs": [
    {
      "label": "build",
      "stream": "stdout",
      "text": "\u001b[36mvite v7.3.5 \u001b[32mbuilding client environment for production...\u001b[36m\u001b[39m"
    },
    {
      "label": "build",
      "stream": "stdout",
      "text": "transforming..."
    },
    {
      "label": "build",
      "stream": "stdout",
      "text": "\u001b[32m✓\u001b[39m 1736 modules transformed."
    },
    {
      "label": "build",
      "stream": "stdout",
      "text": "rendering chunks..."
    },
    {
      "label": "build",
      "stream": "stdout",
      "text": "computing gzip size..."
    },
    {
      "label": "build",
      "stream": "stdout",
      "text": "\u001b[2mdist/\u001b[22m\u001b[32mindex.html                 \u001b[39m\u001b[1m\u001b[2m  0.48 kB\u001b[22m\u001b[1m\u001b[22m\u001b[2m │ gzip:  0.31 kB\u001b[22m"
    },
    {
      "label": "build",
      "stream": "stdout",
      "text": "\u001b[2mdist/\u001b[22m\u001b[35massets/index-DRnmGvkc.css  \u001b[39m\u001b[1m\u001b[2m 70.52 kB\u001b[22m\u001b[1m\u001b[22m\u001b[2m │ gzip: 13.60 kB\u001b[22m\n\u001b[2mdist/\u001b[22m\u001b[36massets/index-Dbz-l4Ac.js   \u001b[39m\u001b[1m\u001b[2m289.44 kB\u001b[22m\u001b[1m\u001b[22m\u001b[2m │ gzip: 89.31 kB\u001b[22m"
    },
    {
      "label": "build",
      "stream": "stdout",
      "text": "\u001b[32m✓ built in 1.61s\u001b[39m"
    },
    {
      "label": "build",
      "stream": "exit",
      "text": "code=0 signal="
    },
    {
      "label": "backend",
      "stream": "stderr",
      "text": "(node:2664) ExperimentalWarning: SQLite is an experimental feature and might change at any time\n(Use `node --trace-warnings ...` to show where the warning was created)"
    },
    {
      "label": "backend",
      "stream": "stdout",
      "text": "codex-workbench-web backend listening on http://127.0.0.1:8787"
    },
    {
      "label": "frontend",
      "stream": "stdout",
      "text": "static frontend listening on http://127.0.0.1:9999"
    }
  ],
  "enterDebug": null,
  "screenshots": {
    "done": "F:\\字节比赛\\最终程序\\reporting\\standalone-artifacts-done.png",
    "retry": "F:\\字节比赛\\最终程序\\reporting\\standalone-artifacts-retry.png"
  }
}